{"accounts_12m_growth":0.950631,"average_last_7_days_transactions":1894066.857143,"circulating_supply":2283097023,"countries":[{"code":"PH"},{"code":"PT"},{"code":"CR"},{"code":"NG"},{"code":"VN"},{"code":"PA"},{"code":"MX"},{"code":"KR"},{"code":"GH"},{"code":"IL"},{"code":"DE"},{"code":"AR"},{"code":"DO"},{"code":"AE"},{"code":"TH"},{"code":"KE"},{"code":"US"},{"code":"UG"},{"code":"IE"},{"code":"CL"},{"code":"NO"},{"code":"ES"},{"code":"MY"},{"code":"ID"},{"code":"BR"},{"code":"PL"},{"code":"JP"},{"code":"FR"},{"code":"ZW"},{"code":"DK"},{"code":"SG"},{"code":"GB"},{"code":"BJ"},{"code":"HR"},{"code":"AT"},{"code":"TW"},{"code":"SD"},{"code":"ZA"},{"code":"NL"},{"code":"PE"},{"code":"CO"},{"code":"HK"},{"code":"EC"},{"code":"GT"},{"code":"IT"},{"code":"IN"},{"code":"SA"}],"countries_eligibile_for_reauth":[{"code":"GB"},{"code":"SG"},{"code":"CR"},{"code":"PE"},{"code":"TW"},{"code":"PT"},{"code":"MY"},{"code":"JP"},{"code":"GT"},{"code":"PA"},{"code":"CL"},{"code":"AR"},{"code":"MX"},{"code":"KR"}],"days_since_launch":873,"last_30_days_active_users":7725583,"last_7_days_accounts":67030,"last_7_days_active_users":3678829,"last_7_days_verifications":24011,"last_day_active_users":998311,"n_continents":6,"n_countries":47,"n_crypto_trades":18721294,"n_grant_claims":113023220,"n_locations_last_7_days":791,"n_orb_manufactured":7735,"n_planets":1,"n_transfers_sent":138958631,"n_verifications":17630881,"n_wallet_transactions_since_launch":867720783,"n_wld_claimed_since_launch":690019850,"n_wld_total_distributed_since_launch":859874090,"n_world_app_countries":"+160","snapshot_timestamp":"2025-12-13 01:40:39.998 Z","total_assets_in_usd":8.073665093864283e+07,"total_mini_apps_approved":468,"total_mini_apps_downloads":111719016,"total_mini_apps_impressions":32117315409,"total_world_ids":37772212,"unique_holders":{"ORB":451446,"OXAUT":4279,"PRZWLD":46670,"RE7USDC":51368,"RE7WBTC":2589,"RE7WETH":10401,"RE7WLD":269868,"U1INCH":5,"UAAVE":25,"UADA":851,"UALGO":31,"UAPE":1,"UAPT":31,"UARB":58,"UATOM":44,"UAVAX":65,"UAXS":8,"UBCH":1,"UBERA":1,"UBLUR":1,"UBONK":63,"UCOMP":1,"UCRO":50,"UCRV":5,"UDOGE":10871,"UDOT":44,"UEGLD":13,"UENS":7,"UETHFI":1,"UFET":28,"UFIL":28,"UFLOKI":30,"UFLOW":8,"UFLR":51,"UGMT":3,"UGRT":9,"UHBAR":111,"UHNT":6,"UICP":242,"UIMX":13,"UINJ":12,"UIP":26,"UJASMY":13,"UJTO":15,"UKSM":1,"ULDO":2,"ULINK":1924,"ULPT":4,"ULTC":741,"UMINA":1,"UMKR":5,"UNEAR":54,"UONDO":53,"UOP":22,"UPENGU":49,"UPEPE":240,"UPNUT":234,"UPOL":47,"UPUMP":1,"UQNT":33,"URNDR":2,"UROSE":3,"USDCE":1540064,"USEI":30,"USHIB":1347,"USNX":1,"USOL":13076,"USTRK":121,"USTX":5,"USUI":3257,"UTAO":41,"UTIA":14,"UTRUMP":91,"UUNI":82,"UVET":71,"UWIF":1,"UXLM":976,"UXRP":11622,"UXTZ":5,"UZK":14,"WARS":172,"WBRL":47,"WBTC":292888,"WETH":191578,"WLD":10519558},"unique_verified_holders":{"ORB":450295,"OXAUT":4217,"PRZWLD":46670,"RE7USDC":50674,"RE7WBTC":2569,"RE7WETH":10295,"RE7WLD":268064,"U1INCH":3,"UAAVE":25,"UADA":841,"UALGO":28,"UAPE":0,"UAPT":30,"UARB":56,"UATOM":42,"UAVAX":64,"UAXS":8,"UBCH":0,"UBERA":0,"UBLUR":0,"UBONK":59,"UCOMP":1,"UCRO":48,"UCRV":5,"UDOGE":10689,"UDOT":42,"UEGLD":12,"UENS":6,"UETHFI":0,"UFET":27,"UFIL":27,"UFLOKI":28,"UFLOW":7,"UFLR":45,"UGMT":3,"UGRT":7,"UHBAR":109,"UHNT":5,"UICP":235,"UIMX":13,"UINJ":11,"UIP":25,"UJASMY":11,"UJTO":14,"UKSM":0,"ULDO":2,"ULINK":1885,"ULPT":4,"ULTC":725,"UMINA":1,"UMKR":4,"UNEAR":52,"UONDO":51,"UOP":21,"UPENGU":45,"UPEPE":232,"UPNUT":230,"UPOL":45,"UPUMP":1,"UQNT":32,"URNDR":1,"UROSE":2,"USDCE":1512554,"USEI":29,"USHIB":1317,"USNX":1,"USOL":12813,"USTRK":118,"USTX":5,"USUI":3217,"UTAO":39,"UTIA":14,"UTRUMP":88,"UUNI":81,"UVET":68,"UWIF":1,"UXLM":956,"UXRP":11442,"UXTZ":5,"UZK":12,"WARS":166,"WBRL":46,"WBTC":289557,"WETH":189309,"WLD":10438879},"unique_wld_holders":10519558,"verifications_12m_growth":0.980468,"verifications_current_day":109,"verifications_current_month":41408,"verifications_current_week":17086,"verifications_last_24_hour":3656,"wallet_transactions_12m_growth":3.594011,"world_id_countries":236}
