{"accounts_12m_growth":0.526167,"average_last_7_days_transactions":869398.625,"circulating_supply":2645181568,"countries":[{"code":"DO"},{"code":"FR"},{"code":"US"},{"code":"PA"},{"code":"AE"},{"code":"DK"},{"code":"KE"},{"code":"JP"},{"code":"ES"},{"code":"CL"},{"code":"ZA"},{"code":"NO"},{"code":"DE"},{"code":"GT"},{"code":"IN"},{"code":"PE"},{"code":"GB"},{"code":"MX"},{"code":"AR"},{"code":"PT"},{"code":"AT"},{"code":"TH"},{"code":"IE"},{"code":"PH"},{"code":"BR"},{"code":"SD"},{"code":"EC"},{"code":"KR"},{"code":"NG"},{"code":"GH"},{"code":"HK"},{"code":"BJ"},{"code":"UG"},{"code":"HR"},{"code":"CR"},{"code":"TW"},{"code":"SA"},{"code":"CO"},{"code":"ZW"},{"code":"ID"},{"code":"PL"},{"code":"MY"},{"code":"IT"},{"code":"NL"},{"code":"VN"},{"code":"SG"},{"code":"IL"}],"countries_eligibile_for_reauth":[{"code":"PT"},{"code":"AR"},{"code":"MX"},{"code":"US"},{"code":"JP"},{"code":"GB"},{"code":"SG"},{"code":"KR"},{"code":"CR"}],"days_since_launch":994,"last_30_days_active_users":4793716,"last_7_days_accounts":62574,"last_7_days_active_users":2119650,"last_7_days_verifications":13593,"last_day_active_users":487207,"n_continents":6,"n_countries":47,"n_crypto_trades":19289360,"n_grant_claims":127564566,"n_locations_last_7_days":394,"n_orb_manufactured":10736,"n_planets":1,"n_transfers_sent":151988137,"n_verifications":17967265,"n_wallet_transactions_since_launch":1036593048,"n_wld_claimed_since_launch":741933236,"n_wld_total_distributed_since_launch":924247516,"n_world_app_countries":"+160","snapshot_timestamp":"2026-04-13 03:20:49.676 Z","total_assets_in_usd":5.252010573229022e+07,"total_mini_apps_approved":603,"total_mini_apps_downloads":118646362,"total_mini_apps_impressions":33690234610,"total_vault_yield_in_usd":6.919332381093505e+06,"total_world_ids":38835297,"unique_holders":{"ORB":626716,"OXAUT":13167,"PRZWLD":63215,"RE7USDC":77551,"RE7WBTC":4778,"RE7WETH":15209,"RE7WLD":398618,"U1INCH":43,"UAAVE":107,"UADA":1240,"UALGO":82,"UAPE":37,"UAPT":78,"UARB":141,"UATOM":111,"UAVAX":172,"UAXS":216,"UBCH":1,"UBERA":197,"UBLUR":58,"UBONK":276,"UCOMP":43,"UCRO":126,"UCRV":53,"UDOGE":14564,"UDOT":133,"UEGLD":47,"UENS":51,"UETHFI":35,"UFET":173,"UFIL":66,"UFLOKI":215,"UFLOW":288,"UFLR":105,"UGMT":106,"UGRT":56,"UHBAR":257,"UHNT":130,"UICP":449,"UIMX":75,"UINJ":48,"UIP":208,"UJASMY":119,"UJTO":78,"UKSM":42,"ULDO":34,"ULINK":2587,"ULPT":49,"ULTC":1093,"UMINA":66,"UMKR":107,"UNEAR":205,"UONDO":225,"UOP":100,"UPENGU":213,"UPEPE":850,"UPNUT":377,"UPOL":221,"UPUMP":213,"UQNT":99,"UREZ":205,"URNDR":4,"UROSE":215,"USDCE":1768083,"USEI":83,"USHIB":1964,"USNX":34,"USOL":19047,"USTRK":138,"USTX":56,"USUI":4408,"UTAO":268,"UTIA":50,"UTRUMP":397,"UUNI":154,"UVET":147,"UWIF":21,"UXLM":1301,"UXRP":16965,"UXTZ":46,"UZK":95,"UZRO":121,"WARS":7957,"WBRL":4031,"WBTC":327099,"WCOP":1331,"WETH":202304,"WLD":10406166,"WMXN":1286},"unique_verified_holders":{"ORB":622457,"OXAUT":13036,"PRZWLD":63215,"RE7USDC":76242,"RE7WBTC":4699,"RE7WETH":14977,"RE7WLD":395056,"U1INCH":39,"UAAVE":105,"UADA":1217,"UALGO":78,"UAPE":36,"UAPT":76,"UARB":134,"UATOM":108,"UAVAX":168,"UAXS":215,"UBCH":0,"UBERA":192,"UBLUR":57,"UBONK":266,"UCOMP":43,"UCRO":118,"UCRV":51,"UDOGE":14316,"UDOT":128,"UEGLD":46,"UENS":50,"UETHFI":32,"UFET":168,"UFIL":65,"UFLOKI":211,"UFLOW":283,"UFLR":97,"UGMT":103,"UGRT":51,"UHBAR":248,"UHNT":128,"UICP":439,"UIMX":71,"UINJ":47,"UIP":203,"UJASMY":115,"UJTO":76,"UKSM":41,"ULDO":30,"ULINK":2531,"ULPT":49,"ULTC":1070,"UMINA":64,"UMKR":103,"UNEAR":200,"UONDO":220,"UOP":99,"UPENGU":208,"UPEPE":834,"UPNUT":366,"UPOL":208,"UPUMP":211,"UQNT":97,"UREZ":202,"URNDR":3,"UROSE":209,"USDCE":1743442,"USEI":80,"USHIB":1916,"USNX":33,"USOL":18632,"USTRK":134,"USTX":54,"USUI":4342,"UTAO":258,"UTIA":48,"UTRUMP":386,"UUNI":150,"UVET":142,"UWIF":21,"UXLM":1273,"UXRP":16663,"UXTZ":46,"UZK":91,"UZRO":120,"WARS":7814,"WBRL":3984,"WBTC":324236,"WCOP":1302,"WETH":200365,"WLD":10314799,"WMXN":1262},"unique_wld_holders":10406166,"verifications_12m_growth":0.50154,"verifications_current_day":36,"verifications_current_month":22360,"verifications_current_week":36,"verifications_last_24_hour":1731,"wallet_transactions_12m_growth":2.181473,"world_id_countries":236}
