{"accounts_12m_growth":0.568017,"average_last_7_days_transactions":1064751.625,"circulating_supply":2570726838,"countries":[{"code":"EC"},{"code":"MX"},{"code":"ZW"},{"code":"GB"},{"code":"MY"},{"code":"TW"},{"code":"NL"},{"code":"SD"},{"code":"JP"},{"code":"AT"},{"code":"NO"},{"code":"SA"},{"code":"NG"},{"code":"BJ"},{"code":"IT"},{"code":"CL"},{"code":"TH"},{"code":"CO"},{"code":"PE"},{"code":"KR"},{"code":"PA"},{"code":"AR"},{"code":"CR"},{"code":"AE"},{"code":"UG"},{"code":"GT"},{"code":"US"},{"code":"KE"},{"code":"PT"},{"code":"DE"},{"code":"ID"},{"code":"IE"},{"code":"HR"},{"code":"GH"},{"code":"DK"},{"code":"VN"},{"code":"BR"},{"code":"PL"},{"code":"HK"},{"code":"ES"},{"code":"PH"},{"code":"FR"},{"code":"IL"},{"code":"DO"},{"code":"SG"},{"code":"IN"},{"code":"ZA"}],"countries_eligibile_for_reauth":[{"code":"SG"},{"code":"CL"},{"code":"GB"},{"code":"PT"},{"code":"CR"},{"code":"AR"},{"code":"MX"},{"code":"PA"},{"code":"KR"},{"code":"JP"},{"code":"GT"},{"code":"US"},{"code":"MY"}],"days_since_launch":965,"last_30_days_active_users":5227093,"last_7_days_accounts":51422,"last_7_days_active_users":2390811,"last_7_days_verifications":17541,"last_day_active_users":600490,"n_continents":6,"n_countries":47,"n_crypto_trades":19169721,"n_grant_claims":124773810,"n_locations_last_7_days":719,"n_orb_manufactured":10112,"n_planets":1,"n_transfers_sent":149707792,"n_verifications":17906860,"n_wallet_transactions_since_launch":1005497463,"n_wld_claimed_since_launch":733843022,"n_wld_total_distributed_since_launch":914358252,"n_world_app_countries":"+160","snapshot_timestamp":"2026-03-15 03:00:54.160 Z","total_assets_in_usd":6.684237880311090e+07,"total_mini_apps_approved":572,"total_mini_apps_downloads":117418874,"total_mini_apps_impressions":33554289649,"total_world_ids":38565996,"unique_holders":{"ORB":681264,"OXAUT":13839,"PRZWLD":69590,"RE7USDC":83935,"RE7WBTC":5094,"RE7WETH":16491,"RE7WLD":430710,"U1INCH":41,"UAAVE":114,"UADA":1366,"UALGO":80,"UAPE":37,"UAPT":82,"UARB":131,"UATOM":110,"UAVAX":175,"UAXS":237,"UBCH":1,"UBERA":216,"UBLUR":48,"UBONK":281,"UCOMP":43,"UCRO":131,"UCRV":54,"UDOGE":15865,"UDOT":134,"UEGLD":51,"UENS":49,"UETHFI":27,"UFET":148,"UFIL":68,"UFLOKI":214,"UFLOW":282,"UFLR":106,"UGMT":100,"UGRT":58,"UHBAR":257,"UHNT":131,"UICP":480,"UIMX":69,"UINJ":49,"UIP":219,"UJASMY":125,"UJTO":75,"UKSM":40,"ULDO":21,"ULINK":2779,"ULPT":55,"ULTC":1161,"UMINA":65,"UMKR":99,"UNEAR":171,"UONDO":192,"UOP":101,"UPENGU":218,"UPEPE":862,"UPNUT":397,"UPOL":221,"UPUMP":214,"UQNT":84,"UREZ":147,"URNDR":5,"UROSE":224,"USDCE":1931024,"USEI":89,"USHIB":2125,"USNX":37,"USOL":20497,"USTRK":152,"USTX":59,"USUI":4821,"UTAO":184,"UTIA":50,"UTRUMP":398,"UUNI":164,"UVET":158,"UWIF":18,"UXLM":1430,"UXRP":18355,"UXTZ":42,"UZK":98,"UZRO":123,"WARS":5308,"WBRL":1636,"WBTC":352725,"WCOP":510,"WETH":220690,"WLD":10713852,"WMXN":428},"unique_verified_holders":{"ORB":677467,"OXAUT":13691,"PRZWLD":69590,"RE7USDC":82559,"RE7WBTC":5020,"RE7WETH":16272,"RE7WLD":426979,"U1INCH":37,"UAAVE":112,"UADA":1341,"UALGO":76,"UAPE":36,"UAPT":79,"UARB":125,"UATOM":107,"UAVAX":171,"UAXS":237,"UBCH":0,"UBERA":211,"UBLUR":47,"UBONK":270,"UCOMP":43,"UCRO":122,"UCRV":51,"UDOGE":15605,"UDOT":129,"UEGLD":50,"UENS":48,"UETHFI":24,"UFET":144,"UFIL":67,"UFLOKI":210,"UFLOW":277,"UFLR":98,"UGMT":99,"UGRT":53,"UHBAR":248,"UHNT":129,"UICP":470,"UIMX":65,"UINJ":48,"UIP":214,"UJASMY":121,"UJTO":73,"UKSM":39,"ULDO":19,"ULINK":2722,"ULPT":55,"ULTC":1137,"UMINA":63,"UMKR":95,"UNEAR":167,"UONDO":187,"UOP":100,"UPENGU":213,"UPEPE":847,"UPNUT":386,"UPOL":208,"UPUMP":211,"UQNT":82,"UREZ":145,"URNDR":4,"UROSE":218,"USDCE":1904911,"USEI":86,"USHIB":2080,"USNX":36,"USOL":20063,"USTRK":148,"USTX":57,"USUI":4759,"UTAO":179,"UTIA":49,"UTRUMP":388,"UUNI":160,"UVET":152,"UWIF":18,"UXLM":1400,"UXRP":18040,"UXTZ":41,"UZK":94,"UZRO":121,"WARS":5195,"WBRL":1613,"WBTC":349724,"WCOP":496,"WETH":218612,"WLD":10616205,"WMXN":418},"unique_wld_holders":10713852,"verifications_12m_growth":0.55733,"verifications_current_day":111,"verifications_current_month":34026,"verifications_current_week":15464,"verifications_last_24_hour":2835,"wallet_transactions_12m_growth":2.456972,"world_id_countries":236}
